[{"type":"Point","coordinates":[-79.4,43.6667],"name":"TORONTO, CA","mindate":"1840-03-01","maxdate":"2017-04-28"},{"type":"Point","coordinates":[-83.38333,33.96667],"name":"ATHENS, GA US","mindate":"1845-01-01","maxdate":"1971-02-28"},{"type":"Point","coordinates":[-77.21667,40.2],"name":"CARLISLE, PA US","mindate":"1846-09-01","maxdate":"1980-09-30"},{"type":"Point","coordinates":[-72.55,41.55],"name":"MIDDLETOWN WEATHER BUREAU, CT US","mindate":"1849-04-01","maxdate":"1958-05-31"},{"type":"Point","coordinates":[-80.65652,34.24291],"name":"CAMDEN 3 W, SC US","mindate":"1849-05-01","maxdate":"2001-09-30"},{"type":"Point","coordinates":[-77.05,38.9],"name":"WASHINGTON DC WEATHER BUREAU CITY, DC US","mindate":"1851-03-01","maxdate":"1965-12-31"},{"type":"Point","coordinates":[-80.4042,37.8566],"name":"LEWISBURG 3 N, WV US","mindate":"1851-04-01","maxdate":"2018-06-24"},{"type":"Point","coordinates":[-121.50472,38.58333],"name":"SACRAMENTO, CA US","mindate":"1856-01-01","maxdate":"1892-12-31"},{"type":"Point","coordinates":[-95.2513,38.9583],"name":"LAWRENCE, KS US","mindate":"1857-04-01","maxdate":"2018-06-23"},{"type":"Point","coordinates":[-87.3795,46.5458],"name":"MARQUETTE, MI US","mindate":"1857-09-01","maxdate":"2018-06-23"},{"type":"Point","coordinates":[-77.06111,38.90028],"name":"WISCONSIN AVE, DC US","mindate":"1860-02-01","maxdate":"1866-01-31"},{"type":"Point","coordinates":[-91.878,42.527],"name":"INDEPENDENCE NUMBER 1, IA US","mindate":"1862-11-01","maxdate":"2009-06-28"},{"type":"Point","coordinates":[-81,43.3833],"name":"STRATFORD, CA","mindate":"1865-01-01","maxdate":"1959-08-31"},{"type":"Point","coordinates":[-74.76667,40.23333],"name":"TRENTON NOTTINGHAMWA, NJ US","mindate":"1865-06-01","maxdate":"1959-06-30"},{"type":"Point","coordinates":[-79.6833,44.4],"name":"BARRIE, CA","mindate":"1866-01-01","maxdate":"1958-06-30"},{"type":"Point","coordinates":[-77.4,44.15],"name":"BELLEVILLE, CA","mindate":"1866-01-01","maxdate":"2018-06-21"},{"type":"Point","coordinates":[-79.9,43.2667],"name":"HAMILTON, CA","mindate":"1866-01-01","maxdate":"1958-08-31"},{"type":"Point","coordinates":[-117.63333,41.96667],"name":"MC DERMITT INDIAN RE, NV US","mindate":"1866-02-01","maxdate":"1949-06-03"},{"type":"Point","coordinates":[-77.15,45.8333],"name":"PEMBROKE EDDY MATCH, CA","mindate":"1866-02-01","maxdate":"1969-06-30"},{"type":"Point","coordinates":[-80.3333,42.8667],"name":"SIMCOE, CA","mindate":"1866-03-01","maxdate":"1961-07-31"},{"type":"Point","coordinates":[-78.3167,44.2833],"name":"PETERBOROUGH, CA","mindate":"1866-04-01","maxdate":"1970-12-31"},{"type":"Point","coordinates":[-82.9333,42.3333],"name":"WINDSOR RIVERSIDE, CA","mindate":"1866-06-01","maxdate":"2018-06-22"},{"type":"Point","coordinates":[-81.7,43.75],"name":"GODERICH, CA","mindate":"1866-12-01","maxdate":"1950-12-31"},{"type":"Point","coordinates":[-80,39.35],"name":"GRAFTON 1 NE, WV US","mindate":"1867-01-01","maxdate":"1963-12-31"},{"type":"Point","coordinates":[-74.7333,45.0167],"name":"CORNWALL, CA","mindate":"1867-01-01","maxdate":"1887-12-31"},{"type":"Point","coordinates":[-120.1574,41.8715],"name":"FORT BIDWELL, CA US","mindate":"1867-06-01","maxdate":"2018-06-17"},{"type":"Point","coordinates":[-80.6,37.1],"name":"RADFORD 5 SW, VA US","mindate":"1867-09-01","maxdate":"1968-04-30"},{"type":"Point","coordinates":[-71.535,43.205],"name":"CONCORD, NH US","mindate":"1868-01-01","maxdate":"1941-04-30"},{"type":"Point","coordinates":[-72.71667,41.55],"name":"MIDDLETOWN 4 W, CT US","mindate":"1868-01-01","maxdate":"2017-12-20"},{"type":"Point","coordinates":[-73.96925,40.77898],"name":"NY CITY CENTRAL PARK, NY US","mindate":"1869-01-01","maxdate":"2018-06-23"},{"type":"Point","coordinates":[-75.866667,37.416667],"name":"BIRDSNEST, VA US","mindate":"1869-01-01","maxdate":"1902-09-26"},{"type":"Point","coordinates":[-82.55167,35.595],"name":"ASHEVILLE ASTON, NC US","mindate":"1869-03-01","maxdate":"1876-07-31"},{"type":"Point","coordinates":[-80.2167,44.4833],"name":"COLLINGWOOD, CA","mindate":"1869-11-01","maxdate":"1974-08-31"},{"type":"Point","coordinates":[-77.5386,35.8847],"name":"TARBORO 1 S, NC US","mindate":"1870-01-01","maxdate":"2018-06-24"},{"type":"Point","coordinates":[-60.2,46.15],"name":"SYDNEY, CA","mindate":"1870-01-01","maxdate":"1941-03-31"},{"type":"Point","coordinates":[-74.1667,45.05],"name":"HUNTINGDON, CA","mindate":"1870-01-01","maxdate":"2008-09-23"},{"type":"Point","coordinates":[-73.966667,40.683333],"name":"BROOKLYN 1, NY US","mindate":"1870-01-01","maxdate":"1890-06-30"},{"type":"Point","coordinates":[-80.7667,43.1333],"name":"WOODSTOCK, CA","mindate":"1870-02-01","maxdate":"2018-06-22"},{"type":"Point","coordinates":[-62.6833,45.7],"name":"PICTOU, CA","mindate":"1870-03-01","maxdate":"1906-04-13"},{"type":"Point","coordinates":[-80.8833,43.05],"name":"INGERSOLL, CA","mindate":"1870-04-01","maxdate":"1969-06-30"},{"type":"Point","coordinates":[-76.2167,45.4667],"name":"FITZROY HARBOUR, CA","mindate":"1870-04-01","maxdate":"1906-10-31"},{"type":"Point","coordinates":[-81.6167,44.1667],"name":"KINCARDINE, CA","mindate":"1870-05-01","maxdate":"2018-06-23"},{"type":"Point","coordinates":[-80.45,43.1833],"name":"PARIS, CA","mindate":"1870-05-01","maxdate":"1967-10-31"},{"type":"Point","coordinates":[-65.75,44.6167],"name":"DIGBY","mindate":"1870-07-01","maxdate":"1965-09-30"},{"type":"Point","coordinates":[-64.3667,45.1],"name":"WOLFVILLE","mindate":"1870-09-01","maxdate":"1949-09-30"},{"type":"Point","coordinates":[-79.3667,44.9167],"name":"GRAVENHURST, CA","mindate":"1870-11-01","maxdate":"1949-09-30"},{"type":"Point","coordinates":[-77.95,34.23333],"name":"WILMINGTON, NC US","mindate":"1870-12-01","maxdate":"1951-09-30"},{"type":"Point","coordinates":[-79.7667,43.7],"name":"BRAMPTON, CA","mindate":"1870-12-01","maxdate":"1964-12-31"},{"type":"Point","coordinates":[-66.0333,43.8333],"name":"YARMOUTH, CA","mindate":"1870-12-01","maxdate":"1941-03-31"},{"type":"Point","coordinates":[-79.3,44.3167],"name":"SUTTON WEST, CA","mindate":"1871-01-01","maxdate":"1908-03-31"}]